[{"carrier":"WN","carrier_name":"Southwest Airlines","dest":"LAS","dest_city":"Las Vegas, NV","flights":6371,"on_time_pct":79.3,"cancel_pct":1.4,"avg_delay":12.2},{"carrier":"WN","carrier_name":"Southwest Airlines","dest":"OAK","dest_city":"Oakland, CA","flights":5931,"on_time_pct":85.6,"cancel_pct":1.5,"avg_delay":8.2},{"carrier":"WN","carrier_name":"Southwest Airlines","dest":"SMF","dest_city":"Sacramento, CA","flights":5401,"on_time_pct":85.3,"cancel_pct":1.5,"avg_delay":7.6},{"carrier":"WN","carrier_name":"Southwest Airlines","dest":"SJC","dest_city":"San Jose, CA","flights":4596,"on_time_pct":85.7,"cancel_pct":1.4,"avg_delay":7.8},{"carrier":"WN","carrier_name":"Southwest Airlines","dest":"PHX","dest_city":"Phoenix, AZ","flights":4340,"on_time_pct":85.2,"cancel_pct":1.2,"avg_delay":8.7},{"carrier":"OO","carrier_name":"SkyWest Airlines","dest":"SFO","dest_city":"San Francisco, CA","flights":3804,"on_time_pct":67.8,"cancel_pct":1.6,"avg_delay":21.7},{"carrier":"AS","carrier_name":"Alaska Airlines","dest":"SEA","dest_city":"Seattle, WA","flights":3118,"on_time_pct":77.5,"cancel_pct":2.1,"avg_delay":12.1},{"carrier":"WN","carrier_name":"Southwest Airlines","dest":"DEN","dest_city":"Denver, CO","flights":2703,"on_time_pct":81.7,"cancel_pct":0.7,"avg_delay":11.9},{"carrier":"NK","carrier_name":"Spirit Airlines","dest":"LAS","dest_city":"Las Vegas, NV","flights":2479,"on_time_pct":77.7,"cancel_pct":2.0,"avg_delay":15.4},{"carrier":"UA","carrier_name":"United Airlines","dest":"SFO","dest_city":"San Francisco, CA","flights":2220,"on_time_pct":73.5,"cancel_pct":1.1,"avg_delay":19.2},{"carrier":"OO","carrier_name":"SkyWest Airlines","dest":"SLC","dest_city":"Salt Lake City, UT","flights":1741,"on_time_pct":91.2,"cancel_pct":0.4,"avg_delay":7.0},{"carrier":"AS","carrier_name":"Alaska Airlines","dest":"PDX","dest_city":"Portland, OR","flights":1606,"on_time_pct":87.0,"cancel_pct":1.8,"avg_delay":7.6},{"carrier":"UA","carrier_name":"United Airlines","dest":"DEN","dest_city":"Denver, CO","flights":1597,"on_time_pct":80.9,"cancel_pct":1.1,"avg_delay":13.4},{"carrier":"AA","carrier_name":"American Airlines","dest":"DFW","dest_city":"Dallas/Fort Worth, TX","flights":1457,"on_time_pct":80.3,"cancel_pct":1.6,"avg_delay":21.0},{"carrier":"OO","carrier_name":"SkyWest Airlines","dest":"PHX","dest_city":"Phoenix, AZ","flights":1074,"on_time_pct":84.1,"cancel_pct":1.0,"avg_delay":17.4},{"carrier":"WN","carrier_name":"Southwest Airlines","dest":"DAL","dest_city":"Dallas, TX","flights":893,"on_time_pct":84.2,"cancel_pct":0.8,"avg_delay":8.9},{"carrier":"WN","carrier_name":"Southwest Airlines","dest":"RNO","dest_city":"Reno, NV","flights":872,"on_time_pct":81.4,"cancel_pct":0.2,"avg_delay":11.3},{"carrier":"WN","carrier_name":"Southwest Airlines","dest":"AUS","dest_city":"Austin, TX","flights":809,"on_time_pct":87.5,"cancel_pct":0.1,"avg_delay":7.8},{"carrier":"WN","carrier_name":"Southwest Airlines","dest":"BNA","dest_city":"Nashville, TN","flights":730,"on_time_pct":87.3,"cancel_pct":0.1,"avg_delay":7.3},{"carrier":"WN","carrier_name":"Southwest Airlines","dest":"ABQ","dest_city":"Albuquerque, NM","flights":699,"on_time_pct":88.3,"cancel_pct":0.3,"avg_delay":6.4},{"carrier":"DL","carrier_name":"Delta Air Lines","dest":"SLC","dest_city":"Salt Lake City, UT","flights":655,"on_time_pct":82.7,"cancel_pct":0.5,"avg_delay":22.9},{"carrier":"WN","carrier_name":"Southwest Airlines","dest":"HOU","dest_city":"Houston, TX","flights":644,"on_time_pct":84.6,"cancel_pct":0.9,"avg_delay":8.4},{"carrier":"OO","carrier_name":"SkyWest Airlines","dest":"STS","dest_city":"Santa Rosa, CA","flights":639,"on_time_pct":76.1,"cancel_pct":2.3,"avg_delay":12.5},{"carrier":"AA","carrier_name":"American Airlines","dest":"PHX","dest_city":"Phoenix, AZ","flights":617,"on_time_pct":80.9,"cancel_pct":0.2,"avg_delay":29.5},{"carrier":"WN","carrier_name":"Southwest Airlines","dest":"MDW","dest_city":"Chicago, IL","flights":610,"on_time_pct":87.0,"cancel_pct":0.3,"avg_delay":8.0},{"carrier":"DL","carrier_name":"Delta Air Lines","dest":"ATL","dest_city":"Atlanta, GA","flights":559,"on_time_pct":75.0,"cancel_pct":1.4,"avg_delay":25.7},{"carrier":"WN","carrier_name":"Southwest Airlines","dest":"STL","dest_city":"St. Louis, MO","flights":531,"on_time_pct":84.6,"cancel_pct":0.6,"avg_delay":8.2},{"carrier":"OO","carrier_name":"SkyWest Airlines","dest":"BOI","dest_city":"Boise, ID","flights":503,"on_time_pct":78.9,"cancel_pct":0.2,"avg_delay":12.1},{"carrier":"B6","carrier_name":"JetBlue Airways","dest":"JFK","dest_city":"New York, NY","flights":479,"on_time_pct":54.1,"cancel_pct":2.3,"avg_delay":47.4},{"carrier":"WN","carrier_name":"Southwest Airlines","dest":"SLC","dest_city":"Salt Lake City, UT","flights":464,"on_time_pct":81.5,"cancel_pct":0.4,"avg_delay":9.9},{"carrier":"NK","carrier_name":"Spirit Airlines","dest":"OAK","dest_city":"Oakland, CA","flights":374,"on_time_pct":80.7,"cancel_pct":1.6,"avg_delay":13.4},{"carrier":"WN","carrier_name":"Southwest Airlines","dest":"MCI","dest_city":"Kansas City, MO","flights":370,"on_time_pct":83.2,"cancel_pct":0.5,"avg_delay":13.1},{"carrier":"WN","carrier_name":"Southwest Airlines","dest":"BOI","dest_city":"Boise, ID","flights":366,"on_time_pct":82.8,"cancel_pct":0.0,"avg_delay":9.4},{"carrier":"MQ","carrier_name":"Envoy Air (American Eagle)","dest":"PHX","dest_city":"Phoenix, AZ","flights":227,"on_time_pct":79.7,"cancel_pct":0.9,"avg_delay":22.4},{"carrier":"WN","carrier_name":"Southwest Airlines","dest":"MSY","dest_city":"New Orleans, LA","flights":212,"on_time_pct":70.8,"cancel_pct":0.0,"avg_delay":14.7},{"carrier":"WN","carrier_name":"Southwest Airlines","dest":"SAT","dest_city":"San Antonio, TX","flights":206,"on_time_pct":77.2,"cancel_pct":0.0,"avg_delay":13.7},{"carrier":"NK","carrier_name":"Spirit Airlines","dest":"SJC","dest_city":"San Jose, CA","flights":204,"on_time_pct":76.0,"cancel_pct":1.0,"avg_delay":12.5},{"carrier":"OO","carrier_name":"SkyWest Airlines","dest":"PDX","dest_city":"Portland, OR","flights":163,"on_time_pct":78.5,"cancel_pct":1.2,"avg_delay":11.5},{"carrier":"WN","carrier_name":"Southwest Airlines","dest":"EUG","dest_city":"Eugene, OR","flights":135,"on_time_pct":77.0,"cancel_pct":0.7,"avg_delay":12.0},{"carrier":"WN","carrier_name":"Southwest Airlines","dest":"PDX","dest_city":"Portland, OR","flights":132,"on_time_pct":81.1,"cancel_pct":0.8,"avg_delay":9.5},{"carrier":"F9","carrier_name":"Frontier Airlines","dest":"DEN","dest_city":"Denver, CO","flights":122,"on_time_pct":76.2,"cancel_pct":0.0,"avg_delay":28.1},{"carrier":"NK","carrier_name":"Spirit Airlines","dest":"SMF","dest_city":"Sacramento, CA","flights":119,"on_time_pct":73.9,"cancel_pct":0.0,"avg_delay":26.0},{"carrier":"F9","carrier_name":"Frontier Airlines","dest":"SFO","dest_city":"San Francisco, CA","flights":109,"on_time_pct":56.0,"cancel_pct":1.8,"avg_delay":31.1},{"carrier":"NK","carrier_name":"Spirit Airlines","dest":"PDX","dest_city":"Portland, OR","flights":91,"on_time_pct":53.8,"cancel_pct":3.3,"avg_delay":30.9},{"carrier":"F9","carrier_name":"Frontier Airlines","dest":"PHX","dest_city":"Phoenix, AZ","flights":74,"on_time_pct":83.8,"cancel_pct":1.4,"avg_delay":7.9},{"carrier":"OO","carrier_name":"SkyWest Airlines","dest":"PSC","dest_city":"Pasco/Kennewick/Richland, WA","flights":66,"on_time_pct":81.8,"cancel_pct":3.0,"avg_delay":10.9},{"carrier":"OO","carrier_name":"SkyWest Airlines","dest":"RDM","dest_city":"Bend/Redmond, OR","flights":66,"on_time_pct":83.3,"cancel_pct":0.0,"avg_delay":9.2},{"carrier":"OO","carrier_name":"SkyWest Airlines","dest":"EUG","dest_city":"Eugene, OR","flights":66,"on_time_pct":77.3,"cancel_pct":1.5,"avg_delay":10.8}]