[{"carrier":"OO","carrier_name":"SkyWest Airlines","dest":"SLC","dest_city":"Salt Lake City, UT","flights":1858,"on_time_pct":93.2,"cancel_pct":0.6,"avg_delay":11.4},{"carrier":"OO","carrier_name":"SkyWest Airlines","dest":"DEN","dest_city":"Denver, CO","flights":1238,"on_time_pct":83.8,"cancel_pct":1.0,"avg_delay":17.9},{"carrier":"OO","carrier_name":"SkyWest Airlines","dest":"LAX","dest_city":"Los Angeles, CA","flights":560,"on_time_pct":88.9,"cancel_pct":1.1,"avg_delay":12.7},{"carrier":"OO","carrier_name":"SkyWest Airlines","dest":"SFO","dest_city":"San Francisco, CA","flights":505,"on_time_pct":63.4,"cancel_pct":1.2,"avg_delay":32.1},{"carrier":"OO","carrier_name":"SkyWest Airlines","dest":"ORD","dest_city":"Chicago, IL","flights":290,"on_time_pct":69.7,"cancel_pct":3.1,"avg_delay":38.2}]