[{"carrier":"OO","carrier_name":"SkyWest Airlines","origin":"DEN","origin_city":"Denver, CO","flights":1053,"on_time_pct":76.9,"cancel_pct":0.9,"avg_delay":16.5},{"carrier":"UA","carrier_name":"United Airlines","origin":"DEN","origin_city":"Denver, CO","flights":976,"on_time_pct":75.0,"cancel_pct":1.5,"avg_delay":19.6},{"carrier":"WN","carrier_name":"Southwest Airlines","origin":"DEN","origin_city":"Denver, CO","flights":907,"on_time_pct":77.7,"cancel_pct":0.9,"avg_delay":13.3},{"carrier":"AA","carrier_name":"American Airlines","origin":"DFW","origin_city":"Dallas/Fort Worth, TX","flights":317,"on_time_pct":69.7,"cancel_pct":0.6,"avg_delay":23.0},{"carrier":"UA","carrier_name":"United Airlines","origin":"ORD","origin_city":"Chicago, IL","flights":219,"on_time_pct":79.0,"cancel_pct":0.0,"avg_delay":13.9},{"carrier":"DL","carrier_name":"Delta Air Lines","origin":"ATL","origin_city":"Atlanta, GA","flights":210,"on_time_pct":84.8,"cancel_pct":1.4,"avg_delay":8.1},{"carrier":"WN","carrier_name":"Southwest Airlines","origin":"DAL","origin_city":"Dallas, TX","flights":170,"on_time_pct":83.5,"cancel_pct":0.6,"avg_delay":10.8},{"carrier":"UA","carrier_name":"United Airlines","origin":"EWR","origin_city":"Newark, NJ","flights":158,"on_time_pct":89.2,"cancel_pct":0.0,"avg_delay":8.7},{"carrier":"OO","carrier_name":"SkyWest Airlines","origin":"LAX","origin_city":"Los Angeles, CA","flights":151,"on_time_pct":77.5,"cancel_pct":0.7,"avg_delay":13.4},{"carrier":"OO","carrier_name":"SkyWest Airlines","origin":"SAN","origin_city":"San Diego, CA","flights":98,"on_time_pct":71.4,"cancel_pct":0.0,"avg_delay":13.2},{"carrier":"OO","carrier_name":"SkyWest Airlines","origin":"IAH","origin_city":"Houston, TX","flights":96,"on_time_pct":77.1,"cancel_pct":2.1,"avg_delay":19.9},{"carrier":"MQ","carrier_name":"Envoy Air (American Eagle)","origin":"ORD","origin_city":"Chicago, IL","flights":94,"on_time_pct":61.7,"cancel_pct":0.0,"avg_delay":14.5},{"carrier":"UA","carrier_name":"United Airlines","origin":"IAH","origin_city":"Houston, TX","flights":86,"on_time_pct":72.1,"cancel_pct":1.2,"avg_delay":16.2},{"carrier":"B6","carrier_name":"JetBlue Airways","origin":"BOS","origin_city":"Boston, MA","flights":67,"on_time_pct":76.1,"cancel_pct":3.0,"avg_delay":11.3},{"carrier":"DL","carrier_name":"Delta Air Lines","origin":"MSP","origin_city":"Minneapolis, MN","flights":64,"on_time_pct":79.7,"cancel_pct":1.6,"avg_delay":15.1},{"carrier":"B6","carrier_name":"JetBlue Airways","origin":"FLL","origin_city":"Fort Lauderdale, FL","flights":53,"on_time_pct":75.5,"cancel_pct":0.0,"avg_delay":12.9}]