[{"carrier":"YX","carrier_name":"Republic Airways","origin":"BOS","origin_city":"Boston, MA","flights":10076,"on_time_pct":78.1,"cancel_pct":3.6,"avg_delay":14.9},{"carrier":"DL","carrier_name":"Delta Air Lines","origin":"ATL","origin_city":"Atlanta, GA","flights":9557,"on_time_pct":77.0,"cancel_pct":1.4,"avg_delay":15.9},{"carrier":"UA","carrier_name":"United Airlines","origin":"ORD","origin_city":"Chicago, IL","flights":9295,"on_time_pct":72.6,"cancel_pct":2.0,"avg_delay":20.9},{"carrier":"AA","carrier_name":"American Airlines","origin":"DFW","origin_city":"Dallas/Fort Worth, TX","flights":7831,"on_time_pct":68.1,"cancel_pct":3.0,"avg_delay":20.9},{"carrier":"YX","carrier_name":"Republic Airways","origin":"DCA","origin_city":"Washington, DC","flights":7602,"on_time_pct":72.8,"cancel_pct":4.0,"avg_delay":18.4},{"carrier":"AA","carrier_name":"American Airlines","origin":"MIA","origin_city":"Miami, FL","flights":6691,"on_time_pct":68.6,"cancel_pct":2.4,"avg_delay":21.6},{"carrier":"AA","carrier_name":"American Airlines","origin":"CLT","origin_city":"Charlotte, NC","flights":6342,"on_time_pct":66.1,"cancel_pct":2.2,"avg_delay":24.7},{"carrier":"AA","carrier_name":"American Airlines","origin":"ORD","origin_city":"Chicago, IL","flights":5682,"on_time_pct":67.6,"cancel_pct":2.5,"avg_delay":27.3},{"carrier":"YX","carrier_name":"Republic Airways","origin":"CMH","origin_city":"Columbus, OH","flights":5543,"on_time_pct":80.9,"cancel_pct":2.4,"avg_delay":12.1},{"carrier":"YX","carrier_name":"Republic Airways","origin":"PIT","origin_city":"Pittsburgh, PA","flights":4950,"on_time_pct":82.2,"cancel_pct":2.6,"avg_delay":11.5},{"carrier":"WN","carrier_name":"Southwest Airlines","origin":"MDW","origin_city":"Chicago, IL","flights":4765,"on_time_pct":72.9,"cancel_pct":2.4,"avg_delay":16.4},{"carrier":"DL","carrier_name":"Delta Air Lines","origin":"ORD","origin_city":"Chicago, IL","flights":4470,"on_time_pct":73.0,"cancel_pct":2.8,"avg_delay":26.2},{"carrier":"YX","carrier_name":"Republic Airways","origin":"IND","origin_city":"Indianapolis, IN","flights":4317,"on_time_pct":83.1,"cancel_pct":2.2,"avg_delay":10.2},{"carrier":"UA","carrier_name":"United Airlines","origin":"IAH","origin_city":"Houston, TX","flights":4297,"on_time_pct":72.1,"cancel_pct":1.7,"avg_delay":20.7},{"carrier":"DL","carrier_name":"Delta Air Lines","origin":"DFW","origin_city":"Dallas/Fort Worth, TX","flights":4247,"on_time_pct":77.4,"cancel_pct":2.1,"avg_delay":21.3},{"carrier":"DL","carrier_name":"Delta Air Lines","origin":"MCO","origin_city":"Orlando, FL","flights":4209,"on_time_pct":75.6,"cancel_pct":2.4,"avg_delay":17.6},{"carrier":"DL","carrier_name":"Delta Air Lines","origin":"DTW","origin_city":"Detroit, MI","flights":3940,"on_time_pct":76.3,"cancel_pct":1.4,"avg_delay":17.3},{"carrier":"UA","carrier_name":"United Airlines","origin":"DEN","origin_city":"Denver, CO","flights":3909,"on_time_pct":74.4,"cancel_pct":1.0,"avg_delay":16.6},{"carrier":"DL","carrier_name":"Delta Air Lines","origin":"MIA","origin_city":"Miami, FL","flights":3691,"on_time_pct":72.7,"cancel_pct":1.9,"avg_delay":21.7},{"carrier":"DL","carrier_name":"Delta Air Lines","origin":"MSP","origin_city":"Minneapolis, MN","flights":3539,"on_time_pct":79.5,"cancel_pct":0.9,"avg_delay":14.5},{"carrier":"DL","carrier_name":"Delta Air Lines","origin":"FLL","origin_city":"Fort Lauderdale, FL","flights":3204,"on_time_pct":75.1,"cancel_pct":2.2,"avg_delay":18.2},{"carrier":"YX","carrier_name":"Republic Airways","origin":"BNA","origin_city":"Nashville, TN","flights":3138,"on_time_pct":76.8,"cancel_pct":2.6,"avg_delay":15.9},{"carrier":"B6","carrier_name":"JetBlue Airways","origin":"FLL","origin_city":"Fort Lauderdale, FL","flights":3104,"on_time_pct":68.3,"cancel_pct":1.7,"avg_delay":23.0},{"carrier":"DL","carrier_name":"Delta Air Lines","origin":"TPA","origin_city":"Tampa, FL","flights":3094,"on_time_pct":72.9,"cancel_pct":2.1,"avg_delay":23.0},{"carrier":"DL","carrier_name":"Delta Air Lines","origin":"PBI","origin_city":"West Palm Beach/Palm Beach, FL","flights":2976,"on_time_pct":75.7,"cancel_pct":2.1,"avg_delay":17.8},{"carrier":"B6","carrier_name":"JetBlue Airways","origin":"BOS","origin_city":"Boston, MA","flights":2975,"on_time_pct":79.0,"cancel_pct":2.6,"avg_delay":14.9},{"carrier":"WN","carrier_name":"Southwest Airlines","origin":"BNA","origin_city":"Nashville, TN","flights":2935,"on_time_pct":76.0,"cancel_pct":1.6,"avg_delay":14.7},{"carrier":"YX","carrier_name":"Republic Airways","origin":"CLE","origin_city":"Cleveland, OH","flights":2917,"on_time_pct":79.4,"cancel_pct":3.5,"avg_delay":13.6},{"carrier":"YX","carrier_name":"Republic Airways","origin":"GSO","origin_city":"Greensboro/High Point, NC","flights":2908,"on_time_pct":77.3,"cancel_pct":3.7,"avg_delay":16.4},{"carrier":"YX","carrier_name":"Republic Airways","origin":"RDU","origin_city":"Raleigh/Durham, NC","flights":2863,"on_time_pct":69.9,"cancel_pct":3.7,"avg_delay":24.5},{"carrier":"YX","carrier_name":"Republic Airways","origin":"RIC","origin_city":"Richmond, VA","flights":2813,"on_time_pct":73.5,"cancel_pct":3.4,"avg_delay":19.0},{"carrier":"B6","carrier_name":"JetBlue Airways","origin":"MCO","origin_city":"Orlando, FL","flights":2809,"on_time_pct":67.5,"cancel_pct":1.6,"avg_delay":26.8},{"carrier":"YX","carrier_name":"Republic Airways","origin":"BUF","origin_city":"Buffalo, NY","flights":2795,"on_time_pct":79.1,"cancel_pct":3.9,"avg_delay":13.3},{"carrier":"WN","carrier_name":"Southwest Airlines","origin":"ATL","origin_city":"Atlanta, GA","flights":2794,"on_time_pct":73.0,"cancel_pct":1.6,"avg_delay":18.3},{"carrier":"WN","carrier_name":"Southwest Airlines","origin":"DAL","origin_city":"Dallas, TX","flights":2773,"on_time_pct":72.8,"cancel_pct":1.6,"avg_delay":18.6},{"carrier":"WN","carrier_name":"Southwest Airlines","origin":"STL","origin_city":"St. Louis, MO","flights":2712,"on_time_pct":75.4,"cancel_pct":2.1,"avg_delay":14.3},{"carrier":"WN","carrier_name":"Southwest Airlines","origin":"DEN","origin_city":"Denver, CO","flights":2700,"on_time_pct":71.3,"cancel_pct":1.1,"avg_delay":18.6},{"carrier":"YX","carrier_name":"Republic Airways","origin":"SDF","origin_city":"Louisville, KY","flights":2699,"on_time_pct":84.8,"cancel_pct":1.5,"avg_delay":9.9},{"carrier":"DL","carrier_name":"Delta Air Lines","origin":"IAH","origin_city":"Houston, TX","flights":2677,"on_time_pct":76.2,"cancel_pct":1.9,"avg_delay":21.0},{"carrier":"WN","carrier_name":"Southwest Airlines","origin":"HOU","origin_city":"Houston, TX","flights":2579,"on_time_pct":75.3,"cancel_pct":1.6,"avg_delay":16.8},{"carrier":"NK","carrier_name":"Spirit Airlines","origin":"FLL","origin_city":"Fort Lauderdale, FL","flights":2383,"on_time_pct":75.6,"cancel_pct":1.6,"avg_delay":16.1},{"carrier":"YX","carrier_name":"Republic Airways","origin":"ORF","origin_city":"Norfolk, VA","flights":2353,"on_time_pct":75.8,"cancel_pct":3.6,"avg_delay":17.4},{"carrier":"B6","carrier_name":"JetBlue Airways","origin":"PBI","origin_city":"West Palm Beach/Palm Beach, FL","flights":2250,"on_time_pct":72.1,"cancel_pct":2.3,"avg_delay":21.4},{"carrier":"NK","carrier_name":"Spirit Airlines","origin":"DTW","origin_city":"Detroit, MI","flights":2247,"on_time_pct":80.1,"cancel_pct":2.3,"avg_delay":13.7},{"carrier":"YX","carrier_name":"Republic Airways","origin":"IAD","origin_city":"Washington, DC","flights":2227,"on_time_pct":73.2,"cancel_pct":3.9,"avg_delay":16.2},{"carrier":"DL","carrier_name":"Delta Air Lines","origin":"DEN","origin_city":"Denver, CO","flights":2082,"on_time_pct":76.9,"cancel_pct":2.1,"avg_delay":19.0},{"carrier":"9E","carrier_name":"Endeavor Air (Delta Connection)","origin":"RDU","origin_city":"Raleigh/Durham, NC","flights":2059,"on_time_pct":77.7,"cancel_pct":3.2,"avg_delay":19.5},{"carrier":"YX","carrier_name":"Republic Airways","origin":"PWM","origin_city":"Portland, ME","flights":2009,"on_time_pct":79.3,"cancel_pct":3.0,"avg_delay":15.3},{"carrier":"YX","carrier_name":"Republic Airways","origin":"MEM","origin_city":"Memphis, TN","flights":1928,"on_time_pct":80.4,"cancel_pct":2.6,"avg_delay":13.1},{"carrier":"YX","carrier_name":"Republic Airways","origin":"ILM","origin_city":"Wilmington, NC","flights":1891,"on_time_pct":78.3,"cancel_pct":3.9,"avg_delay":16.0},{"carrier":"YX","carrier_name":"Republic Airways","origin":"STL","origin_city":"St. Louis, MO","flights":1877,"on_time_pct":81.6,"cancel_pct":2.5,"avg_delay":14.0},{"carrier":"YX","carrier_name":"Republic Airways","origin":"DTW","origin_city":"Detroit, MI","flights":1854,"on_time_pct":79.6,"cancel_pct":3.3,"avg_delay":14.4},{"carrier":"NK","carrier_name":"Spirit Airlines","origin":"MCO","origin_city":"Orlando, FL","flights":1687,"on_time_pct":75.6,"cancel_pct":2.9,"avg_delay":15.8},{"carrier":"YX","carrier_name":"Republic Airways","origin":"PHL","origin_city":"Philadelphia, PA","flights":1642,"on_time_pct":82.5,"cancel_pct":2.7,"avg_delay":11.2},{"carrier":"YX","carrier_name":"Republic Airways","origin":"GSP","origin_city":"Greer, SC","flights":1619,"on_time_pct":78.2,"cancel_pct":4.1,"avg_delay":14.8},{"carrier":"9E","carrier_name":"Endeavor Air (Delta Connection)","origin":"CVG","origin_city":"Cincinnati, OH","flights":1559,"on_time_pct":83.8,"cancel_pct":2.5,"avg_delay":11.7},{"carrier":"9E","carrier_name":"Endeavor Air (Delta Connection)","origin":"CLT","origin_city":"Charlotte, NC","flights":1504,"on_time_pct":76.8,"cancel_pct":4.3,"avg_delay":18.2},{"carrier":"YX","carrier_name":"Republic Airways","origin":"ORD","origin_city":"Chicago, IL","flights":1497,"on_time_pct":78.8,"cancel_pct":2.3,"avg_delay":14.9},{"carrier":"DL","carrier_name":"Delta Air Lines","origin":"MSY","origin_city":"New Orleans, LA","flights":1455,"on_time_pct":77.7,"cancel_pct":1.8,"avg_delay":19.3},{"carrier":"DL","carrier_name":"Delta Air Lines","origin":"RSW","origin_city":"Fort Myers, FL","flights":1448,"on_time_pct":72.3,"cancel_pct":2.0,"avg_delay":25.7},{"carrier":"YX","carrier_name":"Republic Airways","origin":"XNA","origin_city":"Fayetteville, AR","flights":1400,"on_time_pct":78.2,"cancel_pct":3.0,"avg_delay":17.2},{"carrier":"AA","carrier_name":"American Airlines","origin":"DCA","origin_city":"Washington, DC","flights":1370,"on_time_pct":65.5,"cancel_pct":3.3,"avg_delay":31.3},{"carrier":"YX","carrier_name":"Republic Airways","origin":"CVG","origin_city":"Cincinnati, OH","flights":1361,"on_time_pct":79.6,"cancel_pct":2.7,"avg_delay":14.1},{"carrier":"F9","carrier_name":"Frontier Airlines","origin":"ATL","origin_city":"Atlanta, GA","flights":1350,"on_time_pct":62.6,"cancel_pct":3.3,"avg_delay":31.6},{"carrier":"9E","carrier_name":"Endeavor Air (Delta Connection)","origin":"STL","origin_city":"St. Louis, MO","flights":1322,"on_time_pct":83.1,"cancel_pct":3.9,"avg_delay":11.4},{"carrier":"YX","carrier_name":"Republic Airways","origin":"OKC","origin_city":"Oklahoma City, OK","flights":1319,"on_time_pct":76.2,"cancel_pct":3.3,"avg_delay":19.7},{"carrier":"DL","carrier_name":"Delta Air Lines","origin":"MCI","origin_city":"Kansas City, MO","flights":1310,"on_time_pct":78.7,"cancel_pct":1.8,"avg_delay":21.7},{"carrier":"YX","carrier_name":"Republic Airways","origin":"CLT","origin_city":"Charlotte, NC","flights":1299,"on_time_pct":79.9,"cancel_pct":1.8,"avg_delay":15.9},{"carrier":"DL","carrier_name":"Delta Air Lines","origin":"BOS","origin_city":"Boston, MA","flights":1268,"on_time_pct":86.4,"cancel_pct":1.8,"avg_delay":13.4},{"carrier":"WN","carrier_name":"Southwest Airlines","origin":"MCI","origin_city":"Kansas City, MO","flights":1244,"on_time_pct":79.3,"cancel_pct":2.4,"avg_delay":12.5},{"carrier":"NK","carrier_name":"Spirit Airlines","origin":"CLT","origin_city":"Charlotte, NC","flights":1211,"on_time_pct":66.8,"cancel_pct":2.7,"avg_delay":27.1},{"carrier":"YX","carrier_name":"Republic Airways","origin":"GRR","origin_city":"Grand Rapids, MI","flights":1167,"on_time_pct":78.8,"cancel_pct":2.6,"avg_delay":12.8},{"carrier":"NK","carrier_name":"Spirit Airlines","origin":"ORD","origin_city":"Chicago, IL","flights":1117,"on_time_pct":70.6,"cancel_pct":2.2,"avg_delay":23.2},{"carrier":"B6","carrier_name":"JetBlue Airways","origin":"TPA","origin_city":"Tampa, FL","flights":1105,"on_time_pct":66.4,"cancel_pct":3.1,"avg_delay":29.8},{"carrier":"DL","carrier_name":"Delta Air Lines","origin":"SRQ","origin_city":"Sarasota/Bradenton, FL","flights":1093,"on_time_pct":75.5,"cancel_pct":3.0,"avg_delay":32.6},{"carrier":"YX","carrier_name":"Republic Airways","origin":"TYS","origin_city":"Knoxville, TN","flights":1090,"on_time_pct":76.3,"cancel_pct":3.3,"avg_delay":20.6},{"carrier":"AA","carrier_name":"American Airlines","origin":"MCO","origin_city":"Orlando, FL","flights":1075,"on_time_pct":69.8,"cancel_pct":1.7,"avg_delay":26.4},{"carrier":"B6","carrier_name":"JetBlue Airways","origin":"ATL","origin_city":"Atlanta, GA","flights":1067,"on_time_pct":71.0,"cancel_pct":2.1,"avg_delay":25.3},{"carrier":"9E","carrier_name":"Endeavor Air (Delta Connection)","origin":"CLE","origin_city":"Cleveland, OH","flights":1022,"on_time_pct":79.3,"cancel_pct":4.2,"avg_delay":23.1},{"carrier":"NK","carrier_name":"Spirit Airlines","origin":"MYR","origin_city":"Myrtle Beach, SC","flights":1006,"on_time_pct":77.0,"cancel_pct":3.0,"avg_delay":17.6},{"carrier":"AA","carrier_name":"American Airlines","origin":"RDU","origin_city":"Raleigh/Durham, NC","flights":996,"on_time_pct":74.7,"cancel_pct":2.8,"avg_delay":26.9},{"carrier":"NK","carrier_name":"Spirit Airlines","origin":"MIA","origin_city":"Miami, FL","flights":984,"on_time_pct":68.9,"cancel_pct":2.6,"avg_delay":25.2},{"carrier":"YX","carrier_name":"Republic Airways","origin":"CHS","origin_city":"Charleston, SC","flights":984,"on_time_pct":78.8,"cancel_pct":2.4,"avg_delay":15.9},{"carrier":"9E","carrier_name":"Endeavor Air (Delta Connection)","origin":"GSO","origin_city":"Greensboro/High Point, NC","flights":979,"on_time_pct":82.8,"cancel_pct":3.6,"avg_delay":11.2},{"carrier":"9E","carrier_name":"Endeavor Air (Delta Connection)","origin":"RIC","origin_city":"Richmond, VA","flights":976,"on_time_pct":72.6,"cancel_pct":3.4,"avg_delay":18.6},{"carrier":"9E","carrier_name":"Endeavor Air (Delta Connection)","origin":"GSP","origin_city":"Greer, SC","flights":971,"on_time_pct":85.3,"cancel_pct":2.8,"avg_delay":12.4},{"carrier":"YX","carrier_name":"Republic Airways","origin":"MSP","origin_city":"Minneapolis, MN","flights":958,"on_time_pct":77.9,"cancel_pct":3.1,"avg_delay":13.4},{"carrier":"YX","carrier_name":"Republic Airways","origin":"OMA","origin_city":"Omaha, NE","flights":950,"on_time_pct":83.7,"cancel_pct":3.3,"avg_delay":15.1},{"carrier":"9E","carrier_name":"Endeavor Air (Delta Connection)","origin":"ROC","origin_city":"Rochester, NY","flights":941,"on_time_pct":81.6,"cancel_pct":3.9,"avg_delay":12.3},{"carrier":"9E","carrier_name":"Endeavor Air (Delta Connection)","origin":"TYS","origin_city":"Knoxville, TN","flights":941,"on_time_pct":86.4,"cancel_pct":3.5,"avg_delay":8.3},{"carrier":"9E","carrier_name":"Endeavor Air (Delta Connection)","origin":"BHM","origin_city":"Birmingham, AL","flights":938,"on_time_pct":82.0,"cancel_pct":3.8,"avg_delay":10.9},{"carrier":"YX","carrier_name":"Republic Airways","origin":"MSN","origin_city":"Madison, WI","flights":924,"on_time_pct":85.7,"cancel_pct":1.9,"avg_delay":9.9},{"carrier":"9E","carrier_name":"Endeavor Air (Delta Connection)","origin":"CHO","origin_city":"Charlottesville, VA","flights":918,"on_time_pct":76.9,"cancel_pct":4.1,"avg_delay":16.7},{"carrier":"OO","carrier_name":"SkyWest Airlines","origin":"BNA","origin_city":"Nashville, TN","flights":907,"on_time_pct":84.2,"cancel_pct":1.9,"avg_delay":13.8},{"carrier":"9E","carrier_name":"Endeavor Air (Delta Connection)","origin":"BGR","origin_city":"Bangor, ME","flights":904,"on_time_pct":85.5,"cancel_pct":4.2,"avg_delay":8.5},{"carrier":"9E","carrier_name":"Endeavor Air (Delta Connection)","origin":"SAV","origin_city":"Savannah, GA","flights":896,"on_time_pct":81.5,"cancel_pct":3.9,"avg_delay":12.7},{"carrier":"NK","carrier_name":"Spirit Airlines","origin":"IAH","origin_city":"Houston, TX","flights":891,"on_time_pct":69.7,"cancel_pct":1.9,"avg_delay":24.2},{"carrier":"9E","carrier_name":"Endeavor Air (Delta Connection)","origin":"BUF","origin_city":"Buffalo, NY","flights":888,"on_time_pct":81.6,"cancel_pct":3.8,"avg_delay":14.3},{"carrier":"YX","carrier_name":"Republic Airways","origin":"JAX","origin_city":"Jacksonville, FL","flights":833,"on_time_pct":84.3,"cancel_pct":2.4,"avg_delay":13.2},{"carrier":"YX","carrier_name":"Republic Airways","origin":"AVL","origin_city":"Asheville, NC","flights":831,"on_time_pct":75.9,"cancel_pct":3.7,"avg_delay":17.7},{"carrier":"9E","carrier_name":"Endeavor Air (Delta Connection)","origin":"BTV","origin_city":"Burlington, VT","flights":827,"on_time_pct":81.3,"cancel_pct":3.7,"avg_delay":14.0},{"carrier":"YX","carrier_name":"Republic Airways","origin":"CHO","origin_city":"Charlottesville, VA","flights":809,"on_time_pct":69.7,"cancel_pct":3.6,"avg_delay":20.4},{"carrier":"AA","carrier_name":"American Airlines","origin":"TPA","origin_city":"Tampa, FL","flights":808,"on_time_pct":73.0,"cancel_pct":1.7,"avg_delay":29.5},{"carrier":"9E","carrier_name":"Endeavor Air (Delta Connection)","origin":"GRR","origin_city":"Grand Rapids, MI","flights":787,"on_time_pct":81.6,"cancel_pct":4.7,"avg_delay":10.4},{"carrier":"YX","carrier_name":"Republic Airways","origin":"CAE","origin_city":"Columbia, SC","flights":785,"on_time_pct":74.5,"cancel_pct":4.2,"avg_delay":21.1},{"carrier":"YX","carrier_name":"Republic Airways","origin":"SAV","origin_city":"Savannah, GA","flights":783,"on_time_pct":81.7,"cancel_pct":2.3,"avg_delay":15.1},{"carrier":"DL","carrier_name":"Delta Air Lines","origin":"CHS","origin_city":"Charleston, SC","flights":782,"on_time_pct":75.8,"cancel_pct":2.6,"avg_delay":30.7},{"carrier":"9E","carrier_name":"Endeavor Air (Delta Connection)","origin":"IND","origin_city":"Indianapolis, IN","flights":769,"on_time_pct":86.1,"cancel_pct":1.7,"avg_delay":11.3},{"carrier":"9E","carrier_name":"Endeavor Air (Delta Connection)","origin":"ILM","origin_city":"Wilmington, NC","flights":766,"on_time_pct":79.8,"cancel_pct":3.3,"avg_delay":12.0},{"carrier":"OO","carrier_name":"SkyWest Airlines","origin":"MKE","origin_city":"Milwaukee, WI","flights":744,"on_time_pct":81.9,"cancel_pct":2.4,"avg_delay":14.8},{"carrier":"YX","carrier_name":"Republic Airways","origin":"TUL","origin_city":"Tulsa, OK","flights":742,"on_time_pct":83.6,"cancel_pct":2.4,"avg_delay":14.3},{"carrier":"9E","carrier_name":"Endeavor Air (Delta Connection)","origin":"CHS","origin_city":"Charleston, SC","flights":737,"on_time_pct":77.7,"cancel_pct":5.4,"avg_delay":16.5},{"carrier":"9E","carrier_name":"Endeavor Air (Delta Connection)","origin":"MCI","origin_city":"Kansas City, MO","flights":733,"on_time_pct":79.9,"cancel_pct":5.2,"avg_delay":18.7},{"carrier":"YX","carrier_name":"Republic Airways","origin":"LIT","origin_city":"Little Rock, AR","flights":724,"on_time_pct":82.6,"cancel_pct":1.8,"avg_delay":13.3},{"carrier":"OO","carrier_name":"SkyWest Airlines","origin":"OKC","origin_city":"Oklahoma City, OK","flights":711,"on_time_pct":88.3,"cancel_pct":1.8,"avg_delay":8.4},{"carrier":"9E","carrier_name":"Endeavor Air (Delta Connection)","origin":"ORF","origin_city":"Norfolk, VA","flights":689,"on_time_pct":72.4,"cancel_pct":3.6,"avg_delay":18.9},{"carrier":"OO","carrier_name":"SkyWest Airlines","origin":"OMA","origin_city":"Omaha, NE","flights":688,"on_time_pct":79.4,"cancel_pct":2.8,"avg_delay":15.4},{"carrier":"F9","carrier_name":"Frontier Airlines","origin":"DFW","origin_city":"Dallas/Fort Worth, TX","flights":686,"on_time_pct":58.5,"cancel_pct":4.1,"avg_delay":27.9},{"carrier":"9E","carrier_name":"Endeavor Air (Delta Connection)","origin":"MKE","origin_city":"Milwaukee, WI","flights":675,"on_time_pct":81.3,"cancel_pct":2.8,"avg_delay":22.2},{"carrier":"NK","carrier_name":"Spirit Airlines","origin":"DFW","origin_city":"Dallas/Fort Worth, TX","flights":674,"on_time_pct":79.5,"cancel_pct":1.0,"avg_delay":15.7},{"carrier":"WN","carrier_name":"Southwest Airlines","origin":"MSY","origin_city":"New Orleans, LA","flights":672,"on_time_pct":71.7,"cancel_pct":1.9,"avg_delay":16.1},{"carrier":"YX","carrier_name":"Republic Airways","origin":"EYW","origin_city":"Key West, FL","flights":656,"on_time_pct":74.2,"cancel_pct":1.8,"avg_delay":22.1},{"carrier":"9E","carrier_name":"Endeavor Air (Delta Connection)","origin":"ALB","origin_city":"Albany, NY","flights":654,"on_time_pct":87.5,"cancel_pct":2.9,"avg_delay":10.1},{"carrier":"YX","carrier_name":"Republic Airways","origin":"ROA","origin_city":"Roanoke, VA","flights":640,"on_time_pct":63.0,"cancel_pct":6.9,"avg_delay":40.7},{"carrier":"YX","carrier_name":"Republic Airways","origin":"DSM","origin_city":"Des Moines, IA","flights":633,"on_time_pct":81.8,"cancel_pct":2.4,"avg_delay":14.5},{"carrier":"9E","carrier_name":"Endeavor Air (Delta Connection)","origin":"DSM","origin_city":"Des Moines, IA","flights":631,"on_time_pct":80.7,"cancel_pct":3.6,"avg_delay":13.6},{"carrier":"9E","carrier_name":"Endeavor Air (Delta Connection)","origin":"PIT","origin_city":"Pittsburgh, PA","flights":631,"on_time_pct":77.7,"cancel_pct":4.1,"avg_delay":27.3},{"carrier":"YX","carrier_name":"Republic Airways","origin":"ATL","origin_city":"Atlanta, GA","flights":623,"on_time_pct":70.6,"cancel_pct":4.2,"avg_delay":23.5},{"carrier":"9E","carrier_name":"Endeavor Air (Delta Connection)","origin":"MEM","origin_city":"Memphis, TN","flights":597,"on_time_pct":84.6,"cancel_pct":3.7,"avg_delay":13.8},{"carrier":"YX","carrier_name":"Republic Airways","origin":"MVY","origin_city":"Martha's Vineyard, MA","flights":597,"on_time_pct":74.9,"cancel_pct":4.7,"avg_delay":22.1},{"carrier":"YX","carrier_name":"Republic Airways","origin":"ACK","origin_city":"Nantucket, MA","flights":597,"on_time_pct":71.9,"cancel_pct":6.7,"avg_delay":22.2},{"carrier":"F9","carrier_name":"Frontier Airlines","origin":"RDU","origin_city":"Raleigh/Durham, NC","flights":594,"on_time_pct":52.0,"cancel_pct":4.4,"avg_delay":33.6},{"carrier":"NK","carrier_name":"Spirit Airlines","origin":"CMH","origin_city":"Columbus, OH","flights":589,"on_time_pct":75.9,"cancel_pct":3.2,"avg_delay":15.6},{"carrier":"9E","carrier_name":"Endeavor Air (Delta Connection)","origin":"AVL","origin_city":"Asheville, NC","flights":585,"on_time_pct":83.2,"cancel_pct":2.4,"avg_delay":15.7},{"carrier":"F9","carrier_name":"Frontier Airlines","origin":"CLT","origin_city":"Charlotte, NC","flights":577,"on_time_pct":55.5,"cancel_pct":2.4,"avg_delay":38.3},{"carrier":"9E","carrier_name":"Endeavor Air (Delta Connection)","origin":"SYR","origin_city":"Syracuse, NY","flights":550,"on_time_pct":87.1,"cancel_pct":0.9,"avg_delay":10.2},{"carrier":"OO","carrier_name":"SkyWest Airlines","origin":"IAH","origin_city":"Houston, TX","flights":549,"on_time_pct":78.0,"cancel_pct":2.6,"avg_delay":14.0},{"carrier":"9E","carrier_name":"Endeavor Air (Delta Connection)","origin":"MYR","origin_city":"Myrtle Beach, SC","flights":547,"on_time_pct":87.2,"cancel_pct":2.4,"avg_delay":13.4},{"carrier":"9E","carrier_name":"Endeavor Air (Delta Connection)","origin":"CAE","origin_city":"Columbia, SC","flights":544,"on_time_pct":85.7,"cancel_pct":3.5,"avg_delay":9.3},{"carrier":"F9","carrier_name":"Frontier Airlines","origin":"CLE","origin_city":"Cleveland, OH","flights":526,"on_time_pct":68.1,"cancel_pct":4.0,"avg_delay":25.4},{"carrier":"YX","carrier_name":"Republic Airways","origin":"MKE","origin_city":"Milwaukee, WI","flights":523,"on_time_pct":79.0,"cancel_pct":4.0,"avg_delay":15.2},{"carrier":"DL","carrier_name":"Delta Air Lines","origin":"BNA","origin_city":"Nashville, TN","flights":517,"on_time_pct":72.5,"cancel_pct":3.5,"avg_delay":36.5},{"carrier":"9E","carrier_name":"Endeavor Air (Delta Connection)","origin":"PWM","origin_city":"Portland, ME","flights":497,"on_time_pct":78.3,"cancel_pct":4.8,"avg_delay":21.7},{"carrier":"9E","carrier_name":"Endeavor Air (Delta Connection)","origin":"BNA","origin_city":"Nashville, TN","flights":487,"on_time_pct":74.5,"cancel_pct":6.4,"avg_delay":28.8},{"carrier":"AA","carrier_name":"American Airlines","origin":"PBI","origin_city":"West Palm Beach/Palm Beach, FL","flights":485,"on_time_pct":69.9,"cancel_pct":1.2,"avg_delay":28.5},{"carrier":"AA","carrier_name":"American Airlines","origin":"BOS","origin_city":"Boston, MA","flights":482,"on_time_pct":80.7,"cancel_pct":1.9,"avg_delay":20.3},{"carrier":"NK","carrier_name":"Spirit Airlines","origin":"ATL","origin_city":"Atlanta, GA","flights":466,"on_time_pct":88.8,"cancel_pct":1.1,"avg_delay":5.9},{"carrier":"OO","carrier_name":"SkyWest Airlines","origin":"ORD","origin_city":"Chicago, IL","flights":450,"on_time_pct":75.8,"cancel_pct":2.9,"avg_delay":14.6},{"carrier":"9E","carrier_name":"Endeavor Air (Delta Connection)","origin":"JAX","origin_city":"Jacksonville, FL","flights":443,"on_time_pct":88.9,"cancel_pct":1.6,"avg_delay":12.6},{"carrier":"YX","carrier_name":"Republic Airways","origin":"DAY","origin_city":"Dayton, OH","flights":442,"on_time_pct":85.3,"cancel_pct":1.6,"avg_delay":12.6},{"carrier":"F9","carrier_name":"Frontier Airlines","origin":"MCO","origin_city":"Orlando, FL","flights":435,"on_time_pct":71.5,"cancel_pct":1.1,"avg_delay":18.7},{"carrier":"9E","carrier_name":"Endeavor Air (Delta Connection)","origin":"PVD","origin_city":"Providence, RI","flights":410,"on_time_pct":84.9,"cancel_pct":2.9,"avg_delay":21.1},{"carrier":"AA","carrier_name":"American Airlines","origin":"MSY","origin_city":"New Orleans, LA","flights":398,"on_time_pct":60.6,"cancel_pct":1.8,"avg_delay":41.0},{"carrier":"F9","carrier_name":"Frontier Airlines","origin":"DEN","origin_city":"Denver, CO","flights":396,"on_time_pct":59.3,"cancel_pct":3.3,"avg_delay":26.1},{"carrier":"YX","carrier_name":"Republic Airways","origin":"HHH","origin_city":"Hilton Head, SC","flights":384,"on_time_pct":70.3,"cancel_pct":3.6,"avg_delay":39.8},{"carrier":"YX","carrier_name":"Republic Airways","origin":"BGR","origin_city":"Bangor, ME","flights":374,"on_time_pct":79.1,"cancel_pct":6.1,"avg_delay":19.0},{"carrier":"DL","carrier_name":"Delta Air Lines","origin":"MYR","origin_city":"Myrtle Beach, SC","flights":350,"on_time_pct":75.4,"cancel_pct":1.1,"avg_delay":19.6},{"carrier":"AA","carrier_name":"American Airlines","origin":"STL","origin_city":"St. Louis, MO","flights":331,"on_time_pct":76.4,"cancel_pct":3.9,"avg_delay":26.9},{"carrier":"9E","carrier_name":"Endeavor Air (Delta Connection)","origin":"ROA","origin_city":"Roanoke, VA","flights":327,"on_time_pct":88.1,"cancel_pct":2.8,"avg_delay":8.6},{"carrier":"YX","carrier_name":"Republic Airways","origin":"SYR","origin_city":"Syracuse, NY","flights":322,"on_time_pct":79.2,"cancel_pct":2.5,"avg_delay":11.5},{"carrier":"OO","carrier_name":"SkyWest Airlines","origin":"SYR","origin_city":"Syracuse, NY","flights":320,"on_time_pct":71.9,"cancel_pct":3.8,"avg_delay":23.4},{"carrier":"9E","carrier_name":"Endeavor Air (Delta Connection)","origin":"XNA","origin_city":"Fayetteville, AR","flights":310,"on_time_pct":82.9,"cancel_pct":0.6,"avg_delay":14.3},{"carrier":"OO","carrier_name":"SkyWest Airlines","origin":"CLE","origin_city":"Cleveland, OH","flights":306,"on_time_pct":81.0,"cancel_pct":1.0,"avg_delay":17.4},{"carrier":"9E","carrier_name":"Endeavor Air (Delta Connection)","origin":"ORH","origin_city":"Worcester, MA","flights":299,"on_time_pct":79.3,"cancel_pct":5.0,"avg_delay":24.0},{"carrier":"9E","carrier_name":"Endeavor Air (Delta Connection)","origin":"DAY","origin_city":"Dayton, OH","flights":299,"on_time_pct":86.3,"cancel_pct":3.3,"avg_delay":11.3},{"carrier":"F9","carrier_name":"Frontier Airlines","origin":"MIA","origin_city":"Miami, FL","flights":284,"on_time_pct":72.5,"cancel_pct":2.5,"avg_delay":24.3},{"carrier":"F9","carrier_name":"Frontier Airlines","origin":"CVG","origin_city":"Cincinnati, OH","flights":274,"on_time_pct":69.3,"cancel_pct":2.6,"avg_delay":25.6},{"carrier":"B6","carrier_name":"JetBlue Airways","origin":"ACK","origin_city":"Nantucket, MA","flights":262,"on_time_pct":81.3,"cancel_pct":3.1,"avg_delay":16.3},{"carrier":"NK","carrier_name":"Spirit Airlines","origin":"CHS","origin_city":"Charleston, SC","flights":259,"on_time_pct":68.7,"cancel_pct":4.2,"avg_delay":27.4},{"carrier":"AA","carrier_name":"American Airlines","origin":"PIT","origin_city":"Pittsburgh, PA","flights":256,"on_time_pct":73.4,"cancel_pct":1.2,"avg_delay":28.8},{"carrier":"DL","carrier_name":"Delta Air Lines","origin":"RDU","origin_city":"Raleigh/Durham, NC","flights":255,"on_time_pct":65.1,"cancel_pct":3.9,"avg_delay":32.4},{"carrier":"9E","carrier_name":"Endeavor Air (Delta Connection)","origin":"MSN","origin_city":"Madison, WI","flights":247,"on_time_pct":86.6,"cancel_pct":4.0,"avg_delay":8.8},{"carrier":"YX","carrier_name":"Republic Airways","origin":"MCI","origin_city":"Kansas City, MO","flights":242,"on_time_pct":83.5,"cancel_pct":4.1,"avg_delay":8.9},{"carrier":"AA","carrier_name":"American Airlines","origin":"RSW","origin_city":"Fort Myers, FL","flights":237,"on_time_pct":65.0,"cancel_pct":1.7,"avg_delay":34.9},{"carrier":"9E","carrier_name":"Endeavor Air (Delta Connection)","origin":"BDL","origin_city":"Hartford, CT","flights":236,"on_time_pct":80.1,"cancel_pct":4.2,"avg_delay":10.8},{"carrier":"9E","carrier_name":"Endeavor Air (Delta Connection)","origin":"OMA","origin_city":"Omaha, NE","flights":234,"on_time_pct":79.1,"cancel_pct":5.1,"avg_delay":27.3},{"carrier":"B6","carrier_name":"JetBlue Airways","origin":"MSY","origin_city":"New Orleans, LA","flights":233,"on_time_pct":78.1,"cancel_pct":0.0,"avg_delay":28.7},{"carrier":"9E","carrier_name":"Endeavor Air (Delta Connection)","origin":"PNS","origin_city":"Pensacola, FL","flights":231,"on_time_pct":77.9,"cancel_pct":1.3,"avg_delay":23.7},{"carrier":"OO","carrier_name":"SkyWest Airlines","origin":"SDF","origin_city":"Louisville, KY","flights":214,"on_time_pct":70.6,"cancel_pct":7.0,"avg_delay":34.8},{"carrier":"NK","carrier_name":"Spirit Airlines","origin":"BNA","origin_city":"Nashville, TN","flights":211,"on_time_pct":89.1,"cancel_pct":1.4,"avg_delay":6.9},{"carrier":"9E","carrier_name":"Endeavor Air (Delta Connection)","origin":"LIT","origin_city":"Little Rock, AR","flights":201,"on_time_pct":79.1,"cancel_pct":1.5,"avg_delay":15.8},{"carrier":"OO","carrier_name":"SkyWest Airlines","origin":"PIT","origin_city":"Pittsburgh, PA","flights":191,"on_time_pct":61.3,"cancel_pct":6.8,"avg_delay":50.4},{"carrier":"DL","carrier_name":"Delta Air Lines","origin":"CVG","origin_city":"Cincinnati, OH","flights":183,"on_time_pct":77.6,"cancel_pct":3.3,"avg_delay":24.5},{"carrier":"AA","carrier_name":"American Airlines","origin":"SRQ","origin_city":"Sarasota/Bradenton, FL","flights":176,"on_time_pct":80.1,"cancel_pct":1.7,"avg_delay":17.5},{"carrier":"NK","carrier_name":"Spirit Airlines","origin":"PIT","origin_city":"Pittsburgh, PA","flights":175,"on_time_pct":61.1,"cancel_pct":9.7,"avg_delay":37.9},{"carrier":"DL","carrier_name":"Delta Air Lines","origin":"JAX","origin_city":"Jacksonville, FL","flights":173,"on_time_pct":82.7,"cancel_pct":1.2,"avg_delay":12.8},{"carrier":"B6","carrier_name":"JetBlue Airways","origin":"RSW","origin_city":"Fort Myers, FL","flights":167,"on_time_pct":68.3,"cancel_pct":1.2,"avg_delay":30.1},{"carrier":"WN","carrier_name":"Southwest Airlines","origin":"TPA","origin_city":"Tampa, FL","flights":167,"on_time_pct":84.4,"cancel_pct":1.2,"avg_delay":7.3},{"carrier":"YX","carrier_name":"Republic Airways","origin":"HYA","origin_city":"Hyannis, MA","flights":167,"on_time_pct":68.9,"cancel_pct":1.8,"avg_delay":28.6},{"carrier":"OO","carrier_name":"SkyWest Airlines","origin":"ROC","origin_city":"Rochester, NY","flights":167,"on_time_pct":70.7,"cancel_pct":2.4,"avg_delay":26.3},{"carrier":"OO","carrier_name":"SkyWest Airlines","origin":"RDU","origin_city":"Raleigh/Durham, NC","flights":164,"on_time_pct":76.2,"cancel_pct":2.4,"avg_delay":25.7},{"carrier":"AA","carrier_name":"American Airlines","origin":"FLL","origin_city":"Fort Lauderdale, FL","flights":129,"on_time_pct":55.8,"cancel_pct":5.4,"avg_delay":36.2},{"carrier":"NK","carrier_name":"Spirit Airlines","origin":"PBI","origin_city":"West Palm Beach/Palm Beach, FL","flights":119,"on_time_pct":71.4,"cancel_pct":4.2,"avg_delay":17.2},{"carrier":"OO","carrier_name":"SkyWest Airlines","origin":"BUF","origin_city":"Buffalo, NY","flights":113,"on_time_pct":73.5,"cancel_pct":2.7,"avg_delay":16.4},{"carrier":"OO","carrier_name":"SkyWest Airlines","origin":"BTV","origin_city":"Burlington, VT","flights":112,"on_time_pct":86.6,"cancel_pct":0.0,"avg_delay":10.3},{"carrier":"9E","carrier_name":"Endeavor Air (Delta Connection)","origin":"TUL","origin_city":"Tulsa, OK","flights":110,"on_time_pct":86.4,"cancel_pct":0.0,"avg_delay":6.4},{"carrier":"OO","carrier_name":"SkyWest Airlines","origin":"MCI","origin_city":"Kansas City, MO","flights":109,"on_time_pct":71.6,"cancel_pct":6.4,"avg_delay":21.0},{"carrier":"B6","carrier_name":"JetBlue Airways","origin":"MVY","origin_city":"Martha's Vineyard, MA","flights":102,"on_time_pct":68.6,"cancel_pct":4.9,"avg_delay":32.5},{"carrier":"YX","carrier_name":"Republic Airways","origin":"BHM","origin_city":"Birmingham, AL","flights":96,"on_time_pct":89.6,"cancel_pct":2.1,"avg_delay":6.0},{"carrier":"AA","carrier_name":"American Airlines","origin":"DTW","origin_city":"Detroit, MI","flights":95,"on_time_pct":66.3,"cancel_pct":1.1,"avg_delay":25.0},{"carrier":"YX","carrier_name":"Republic Airways","origin":"PBI","origin_city":"West Palm Beach/Palm Beach, FL","flights":95,"on_time_pct":53.7,"cancel_pct":6.3,"avg_delay":49.8},{"carrier":"B6","carrier_name":"JetBlue Airways","origin":"DEN","origin_city":"Denver, CO","flights":92,"on_time_pct":75.0,"cancel_pct":0.0,"avg_delay":26.6},{"carrier":"OO","carrier_name":"SkyWest Airlines","origin":"RIC","origin_city":"Richmond, VA","flights":92,"on_time_pct":51.1,"cancel_pct":3.3,"avg_delay":45.2},{"carrier":"B6","carrier_name":"JetBlue Airways","origin":"SRQ","origin_city":"Sarasota/Bradenton, FL","flights":90,"on_time_pct":75.6,"cancel_pct":3.3,"avg_delay":31.2},{"carrier":"AA","carrier_name":"American Airlines","origin":"BNA","origin_city":"Nashville, TN","flights":87,"on_time_pct":70.1,"cancel_pct":5.7,"avg_delay":56.3},{"carrier":"OO","carrier_name":"SkyWest Airlines","origin":"MSN","origin_city":"Madison, WI","flights":79,"on_time_pct":81.0,"cancel_pct":3.8,"avg_delay":21.0},{"carrier":"YX","carrier_name":"Republic Airways","origin":"MIA","origin_city":"Miami, FL","flights":76,"on_time_pct":67.1,"cancel_pct":0.0,"avg_delay":28.7},{"carrier":"OO","carrier_name":"SkyWest Airlines","origin":"STL","origin_city":"St. Louis, MO","flights":75,"on_time_pct":74.7,"cancel_pct":2.7,"avg_delay":36.0},{"carrier":"OO","carrier_name":"SkyWest Airlines","origin":"IND","origin_city":"Indianapolis, IN","flights":74,"on_time_pct":78.4,"cancel_pct":1.4,"avg_delay":24.2},{"carrier":"9E","carrier_name":"Endeavor Air (Delta Connection)","origin":"TVC","origin_city":"Traverse City, MI","flights":72,"on_time_pct":87.5,"cancel_pct":1.4,"avg_delay":20.8},{"carrier":"YX","carrier_name":"Republic Airways","origin":"BTV","origin_city":"Burlington, VT","flights":70,"on_time_pct":88.6,"cancel_pct":0.0,"avg_delay":13.8},{"carrier":"OO","carrier_name":"SkyWest Airlines","origin":"GRR","origin_city":"Grand Rapids, MI","flights":67,"on_time_pct":76.1,"cancel_pct":3.0,"avg_delay":15.4},{"carrier":"9E","carrier_name":"Endeavor Air (Delta Connection)","origin":"CHA","origin_city":"Chattanooga, TN","flights":63,"on_time_pct":90.5,"cancel_pct":0.0,"avg_delay":12.6},{"carrier":"OO","carrier_name":"SkyWest Airlines","origin":"ORF","origin_city":"Norfolk, VA","flights":62,"on_time_pct":69.4,"cancel_pct":1.6,"avg_delay":19.0},{"carrier":"DL","carrier_name":"Delta Air Lines","origin":"TVC","origin_city":"Traverse City, MI","flights":61,"on_time_pct":85.2,"cancel_pct":3.3,"avg_delay":18.5},{"carrier":"YX","carrier_name":"Republic Airways","origin":"MYR","origin_city":"Myrtle Beach, SC","flights":50,"on_time_pct":84.0,"cancel_pct":2.0,"avg_delay":4.6}]